stika/patterns/observer/__init__.py
stika_patterns_observer-0.9.dist-info/LICENSE
stika_patterns_observer-0.9.dist-info/METADATA
stika_patterns_observer-0.9.dist-info/WHEEL
stika_patterns_observer-0.9.dist-info/top_level.txt
stika_patterns_observer-0.9.dist-info/RECORD
