Metadata-Version: 2.1
Name: stika-patterns-observer
Version: 0.9
Summary: Simple Observer Pattern
Home-page: https://github.com/KalleDK/stika-patterns-observer
Author: Kalle R. Møller
Author-email: pypi@k-moeller.dk
License: MIT License
Requires-Dist: typing-extensions
